setup.py
njserial/__init__.py
njserial/utils.py
njserial/version.py
njserial/xpath.py
njserial.egg-info/PKG-INFO
njserial.egg-info/SOURCES.txt
njserial.egg-info/dependency_links.txt
njserial.egg-info/requires.txt
njserial.egg-info/top_level.txt
njserial.egg-info/zip-safe
njserial/cli/__init__.py
njserial/ext/count.py
njserial/ext/nj_serial.py
njserial/ext/serial_crc.py
njserial/ext/utils/nj_excel.py
njserial/ext/utils/nj_file.py
njserial/ext/utils/nj_parse.py
njserial/ext/utils/nj_re.py
njserial/ext/utils/nj_time.py