Metadata-Version: 1.0
Name: njserial
Version: 1.0.1
Summary: Serial Tool
Home-page: https://github.com/congrenya/njtest/blob/master/njtest.py
Author: Stephen Yao
Author-email: a1123547734@163.com
License: MIT Licence
Keywords: pip,SICA,featureextraction
Platform: any
